ocdb/__init__.py
ocdb/io.py
ocdb/management.py
ocdb/material.py
ocdb/plotting.py
ocdb/processing.py
ocdb/report.py
ocdb/db/COPYING
ocdb/db/literature.bib
ocdb/db/data/Co.txt
ocdb/db/data/Mo.txt
ocdb/db/data/Ni.txt
ocdb/db/data/Ni2Al3.txt
ocdb/db/data/Ni3Al.txt
ocdb/db/data/NiAl.txt
ocdb/db/data/Pt.txt
ocdb/db/data/Pt2Mo.txt
ocdb/db/data/PtMo.txt
ocdb/db/data/PtTe.txt
ocdb/db/data/Ru.txt
ocdb/db/data/Ru2W.txt
ocdb/db/data/Ru3Re.txt
ocdb/db/data/Ru3Ta.txt
ocdb/db/data/RuTa.txt
ocdb/db/data/RuTa3.txt
ocdb/db/data/Ru_2019.txt
ocdb/db/data/Ru_2019.yaml
ocdb/db/data/SiN.txt
ocdb/db/data/SiO2.txt
ocdb/db/data/Ta.txt
ocdb/db/data/Ta2Co.txt
ocdb/db/data/TaBN.txt
ocdb/db/data/TaCo.txt
ocdb/db/data/TaTeN.txt
ocdb/db/data/Ta_2019.txt
ocdb/db/data/Ta_2019.yaml
ocdb/db/data/Te.txt
ocdb/db/data/TiN.txt
ocdb/db/metadata/compositions/Ni2Al3.yaml
ocdb/db/metadata/compositions/Ni3Al.yaml
ocdb/db/metadata/compositions/NiAl.yaml
ocdb/db/metadata/compositions/Pt2Mo.yaml
ocdb/db/metadata/compositions/PtMo.yaml
ocdb/db/metadata/compositions/PtTe.yaml
ocdb/db/metadata/compositions/Ru2W.yaml
ocdb/db/metadata/compositions/Ru3Re.yaml
ocdb/db/metadata/compositions/Ru3Ta.yaml
ocdb/db/metadata/compositions/RuTa.yaml
ocdb/db/metadata/compositions/RuTa3.yaml
ocdb/db/metadata/compositions/SiN.yaml
ocdb/db/metadata/compositions/SiO2.yaml
ocdb/db/metadata/compositions/Ta2Co.yaml
ocdb/db/metadata/compositions/TaBN.yaml
ocdb/db/metadata/compositions/TaCo.yaml
ocdb/db/metadata/compositions/TaTeN.yaml
ocdb/db/metadata/compositions/TiN.yaml
ocdb/db/metadata/elements/Co.yaml
ocdb/db/metadata/elements/Mo.yaml
ocdb/db/metadata/elements/Ni.yaml
ocdb/db/metadata/elements/Pt.yaml
ocdb/db/metadata/elements/Ru.yaml
ocdb/db/metadata/elements/Ta.yaml
ocdb/db/metadata/elements/Te.yaml
ocdb/templates/report/latex/base.tex
ocdb/templates/report/latex/colophon.tex
ocdb/templates/report/latex/literature.bib
ocdb/templates/report/latex/material.tex
ocdb-0.2.1.dist-info/licenses/COPYING
ocdb-0.2.1.dist-info/licenses/LICENSE
ocdb-0.2.1.dist-info/METADATA
ocdb-0.2.1.dist-info/WHEEL
ocdb-0.2.1.dist-info/top_level.txt
ocdb-0.2.1.dist-info/RECORD
