Metadata-Version: 2.4
Name: ocdb
Version: 0.2.1
Summary: Optical constants for elements and various materials in the EUV and VUV wavelengths
Home-page: https://www.ocdb.ptb.de/
Author: Till Biskup
Author-email: till.biskup@ptb.de
License: GPLv3
Project-URL: Documentation, https://ocdb-data.readthedocs.io/
Project-URL: Source, https://github.com/PTB-SR/ocdb
Keywords: optical constants,EUV,VUV,reflectometry
Classifier: Programming Language :: Python :: 3
Classifier: Programming Language :: Python :: 3.9
Classifier: Programming Language :: Python :: 3.10
Classifier: Programming Language :: Python :: 3.11
Classifier: Programming Language :: Python :: 3.12
Classifier: License :: OSI Approved :: GNU General Public License v3 (GPLv3)
Classifier: Operating System :: OS Independent
Classifier: Intended Audience :: Science/Research
Classifier: Development Status :: 4 - Beta
Requires-Python: >=3.9
License-File: LICENSE
License-File: COPYING
Requires-Dist: bibrecord>=0.2.2
Requires-Dist: numpy
Requires-Dist: oyaml
Provides-Extra: presentation
Requires-Dist: matplotlib; extra == "presentation"
Requires-Dist: jinja2; extra == "presentation"
Provides-Extra: dev
Requires-Dist: prospector; extra == "dev"
Requires-Dist: pyroma; extra == "dev"
Requires-Dist: bandit; extra == "dev"
Requires-Dist: black; extra == "dev"
Requires-Dist: pymetacode; extra == "dev"
Provides-Extra: docs
Requires-Dist: sphinx; extra == "docs"
Requires-Dist: sphinx-rtd-theme; extra == "docs"
Requires-Dist: sphinx_multiversion; extra == "docs"
Provides-Extra: deployment
Requires-Dist: build; extra == "deployment"
Requires-Dist: twine; extra == "deployment"
Dynamic: author
Dynamic: author-email
Dynamic: classifier
Dynamic: description
Dynamic: description-content-type
Dynamic: home-page
Dynamic: keywords
Dynamic: license
Dynamic: license-file
Dynamic: project-url
Dynamic: provides-extra
Dynamic: requires-dist
Dynamic: requires-python
Dynamic: summary
